aiozoneinfo/__init__.py
aiozoneinfo/py.typed
aiozoneinfo-0.2.0.dist-info/LICENSE
aiozoneinfo-0.2.0.dist-info/METADATA
aiozoneinfo-0.2.0.dist-info/WHEEL
aiozoneinfo-0.2.0.dist-info/RECORD
