Metadata-Version: 2.1
Name: aiozoneinfo
Version: 0.2.0
Summary: Tools to fetch zoneinfo with asyncio
Home-page: https://github.com/bluetooth-devices/aiozoneinfo
License: Apache Software License 2.0
Author: J. Nick Koston
Author-email: nick@koston.org
Requires-Python: >=3.8,<4.0
Classifier: Development Status :: 2 - Pre-Alpha
Classifier: Intended Audience :: Developers
Classifier: License :: Other/Proprietary License
Classifier: Natural Language :: English
Classifier: Operating System :: OS Independent
Classifier: Programming Language :: Python :: 3
Classifier: Programming Language :: Python :: 3.8
Classifier: Programming Language :: Python :: 3.9
Classifier: Programming Language :: Python :: 3.10
Classifier: Programming Language :: Python :: 3.11
Classifier: Programming Language :: Python :: 3.12
Classifier: Topic :: Software Development :: Libraries
Requires-Dist: backports.zoneinfo (>=0.2.0) ; python_version < "3.9"
Requires-Dist: tzdata (>=2024.1)
Project-URL: Bug Tracker, https://github.com/bluetooth-devices/aiozoneinfo/issues
Project-URL: Changelog, https://github.com/bluetooth-devices/aiozoneinfo/blob/main/CHANGELOG.md
Project-URL: Documentation, https://aiozoneinfo.readthedocs.io
Project-URL: Repository, https://github.com/bluetooth-devices/aiozoneinfo
